modelgauge/annotators/perspective_api.py
modelgauge_perspective_api-0.6.3.dist-info/METADATA
modelgauge_perspective_api-0.6.3.dist-info/WHEEL
modelgauge_perspective_api-0.6.3.dist-info/RECORD
